jcu/__init__.py
jcu/jcu.py
jcu-1.1.dist-info/METADATA
jcu-1.1.dist-info/WHEEL
jcu-1.1.dist-info/entry_points.txt
jcu-1.1.dist-info/top_level.txt
jcu-1.1.dist-info/RECORD
